replink/__init__.py
replink/cli.py
replink/common.py
replink/core.py
replink/logging.py
replink/types.py
replink/languages/__init__.py
replink/languages/common.py
replink/languages/python.py
replink/targets/__init__.py
replink/targets/common.py
replink/targets/tmux.py
replink/targets/zellij.py
replink-0.2.0.dist-info/METADATA
replink-0.2.0.dist-info/WHEEL
replink-0.2.0.dist-info/entry_points.txt
replink-0.2.0.dist-info/licenses/LICENSE.txt
replink-0.2.0.dist-info/RECORD
