Metadata-Version: 2.4
Name: replink
Version: 0.2.0
Summary: A simple CLI for piping code to a REPL running in a separate pane
License-File: LICENSE.txt
Classifier: Development Status :: 3 - Alpha
Classifier: Environment :: Console
Classifier: Intended Audience :: Developers
Classifier: License :: OSI Approved :: MIT License
Classifier: Operating System :: POSIX
Classifier: Operating System :: Unix
Classifier: Programming Language :: Python :: 3
Classifier: Programming Language :: Python :: 3.12
Classifier: Programming Language :: Python :: 3.13
Classifier: Topic :: Software Development
Classifier: Topic :: System :: Shells
Classifier: Topic :: Utilities
Requires-Python: >=3.12
